quantsim/__init__.py
quantsim/cli/__init__.py
quantsim/cli/main.py
quantsim/core/__init__.py
quantsim/core/event_queue.py
quantsim/core/events.py
quantsim/core/simulation_engine.py
quantsim/data/__init__.py
quantsim/data/base.py
quantsim/data/csv_parser.py
quantsim/data/synthetic_data.py
quantsim/data/yahoo_finance.py
quantsim/execution/__init__.py
quantsim/execution/execution_handler.py
quantsim/execution/slippage.py
quantsim/indicators/__init__.py
quantsim/indicators/atr.py
quantsim/indicators/sma.py
quantsim/ml/base_ml_strategy.py
quantsim/ml/feature_generator.py
quantsim/ml/trainer.py
quantsim/portfolio/__init__.py
quantsim/portfolio/portfolio.py
quantsim/portfolio/position.py
quantsim/portfolio/position_sizer.py
quantsim/portfolio/risk_parity_portfolio.py
quantsim/portfolio/trade_log.py
quantsim/reports/__init__.py
quantsim/reports/plotter.py
quantsim/reports/report_generator.py
quantsim/strategies/__init__.py
quantsim/strategies/base.py
quantsim/strategies/mean_reversion.py
quantsim/strategies/momentum.py
quantsim/strategies/pairs_trading.py
quantsim/strategies/simple_ml.py
quantsim/strategies/sma_crossover.py
quantsim/tests/__init__.py
simquant-0.1.0.dist-info/licenses/LICENSE
simquant-0.1.0.dist-info/METADATA
simquant-0.1.0.dist-info/WHEEL
simquant-0.1.0.dist-info/entry_points.txt
simquant-0.1.0.dist-info/top_level.txt
simquant-0.1.0.dist-info/RECORD
