Metadata-Version: 2.4
Name: simQuant
Version: 0.1.0
Summary: An event-driven backtesting and execution simulation engine for quantitative trading strategies.
Author-email: Yash Tripathi <tripathiyash1004@gmail.com>
Maintainer-email: Yash Tripathi <tripathiyash1004@gmail.com>
License-Expression: MIT
Project-URL: Homepage, https://github.com/yash-tr/quantsim
Project-URL: Repository, https://github.com/yash-tr/quantsim
Project-URL: Documentation, https://yash-tr.github.io/quantsim/
Project-URL: Bug Tracker, https://github.com/yash-tr/quantsim/issues
Project-URL: Changelog, https://github.com/yash-tr/quantsim/blob/main/CHANGELOG.md
Keywords: quantitative,trading,finance,backtesting,event-driven,algorithmic trading,simulation,strategies
Classifier: Development Status :: 3 - Alpha
Classifier: Intended Audience :: Developers
Classifier: Intended Audience :: Financial and Insurance Industry
Classifier: Intended Audience :: Science/Research
Classifier: Operating System :: OS Independent
Classifier: Programming Language :: Python :: 3
Classifier: Programming Language :: Python :: 3.9
Classifier: Programming Language :: Python :: 3.10
Classifier: Programming Language :: Python :: 3.11
Classifier: Topic :: Office/Business :: Financial :: Investment
Classifier: Topic :: Scientific/Engineering :: Information Analysis
Classifier: Topic :: Software Development :: Libraries :: Python Modules
Requires-Python: >=3.9
License-File: LICENSE
Requires-Dist: pandas>=1.3
Requires-Dist: numpy>=1.20
Requires-Dist: matplotlib>=3.4
Requires-Dist: PyYAML>=5.4
Requires-Dist: yfinance>=0.2.0
Requires-Dist: joblib>=1.1.0
Provides-Extra: ml
Requires-Dist: scikit-learn>=1.0; extra == "ml"
Requires-Dist: tensorflow>=2.8; extra == "ml"
Provides-Extra: pairs
Requires-Dist: statsmodels>=0.13.0; extra == "pairs"
Provides-Extra: dev
Requires-Dist: pytest>=7.0; extra == "dev"
Requires-Dist: pytest-cov>=3.0; extra == "dev"
Requires-Dist: pytest-mock>=3.0; extra == "dev"
Requires-Dist: black; extra == "dev"
Requires-Dist: flake8; extra == "dev"
Requires-Dist: mypy; extra == "dev"
Requires-Dist: build; extra == "dev"
Requires-Dist: twine; extra == "dev"
Provides-Extra: docs
Requires-Dist: mkdocs>=1.5.0; extra == "docs"
Requires-Dist: mkdocs-material>=9.0.0; extra == "docs"
Requires-Dist: mkdocs-git-revision-date-localized-plugin>=1.2.0; extra == "docs"
Requires-Dist: mkdocs-minify-plugin>=0.7.0; extra == "docs"
Requires-Dist: pymdown-extensions>=10.0.0; extra == "docs"
Requires-Dist: pillow>=9.0.0; extra == "docs"
Requires-Dist: cairosvg>=2.5.0; extra == "docs"
Dynamic: license-file
